silero_vad/__init__.py
silero_vad/core.py
silero_vad_fork-0.1.0.dist-info/LICENSE
silero_vad_fork-0.1.0.dist-info/METADATA
silero_vad_fork-0.1.0.dist-info/WHEEL
silero_vad_fork-0.1.0.dist-info/top_level.txt
silero_vad_fork-0.1.0.dist-info/RECORD
