Metadata-Version: 2.1
Name: silero-vad-fork
Version: 0.1.0
Summary: A packaged version of the Silero VAD model
Author: Silero Team, Peter Baumgartner
License: MIT
License-File: LICENSE
Requires-Dist: torch >=1.12.0
Requires-Dist: torchaudio
Requires-Dist: numpy
Requires-Dist: onnx
Requires-Dist: onnxruntime
Provides-Extra: dev
Requires-Dist: ipython ; extra == 'dev'
Requires-Dist: black ; extra == 'dev'
Requires-Dist: ruff ; extra == 'dev'
